dowser/__init__.py
dowser/dowser.py
dowser/reftree.py
dowser/utils.py
dowser_py3-0.2.1.dist-info/DESCRIPTION.rst
dowser_py3-0.2.1.dist-info/METADATA
dowser_py3-0.2.1.dist-info/RECORD
dowser_py3-0.2.1.dist-info/WHEEL
dowser_py3-0.2.1.dist-info/entry_points.txt
dowser_py3-0.2.1.dist-info/metadata.json
dowser_py3-0.2.1.dist-info/top_level.txt
